turbopdf/__init__.py
turbopdf/core.py
turbopdf/assemblers/__init__.py
turbopdf/assemblers/base.py
turbopdf/assemblers/form.py
turbopdf/assemblers/report.py
turbopdf/fonts/Roboto-Bold.ttf
turbopdf/fonts/Roboto-Regular.ttf
turbopdf/img/Logo-unp-rojo.png
turbopdf/img/logo-mininterior-rojo.jpg
turbopdf/templates/sistema/anexos.html
turbopdf/templates/sistema/anexos_limpio.html
turbopdf/templates/sistema/archivese.html
turbopdf/templates/sistema/autoriza_envio.html
turbopdf/templates/sistema/checkbox.html
turbopdf/templates/sistema/control_cambios.html
turbopdf/templates/sistema/datos_basicosinf.html
turbopdf/templates/sistema/datos_ot.html
turbopdf/templates/sistema/encaso_de.html
turbopdf/templates/sistema/fiila_dos_check.html
turbopdf/templates/sistema/fila_cinco_zona.html
turbopdf/templates/sistema/fila_cuatro.html
turbopdf/templates/sistema/fila_cuatro_si_no.html
turbopdf/templates/sistema/fila_cuatro_zona.html
turbopdf/templates/sistema/fila_dos.html
turbopdf/templates/sistema/fila_dos_zona.html
turbopdf/templates/sistema/fila_instructivo.html
turbopdf/templates/sistema/fila_tres.html
turbopdf/templates/sistema/fila_tres_checkbox.html
turbopdf/templates/sistema/fila_tres_zona.html
turbopdf/templates/sistema/fila_uno.html
turbopdf/templates/sistema/firma.html
turbopdf/templates/sistema/firma_doble.html
turbopdf/templates/sistema/firmaop2.html
turbopdf/templates/sistema/firmas_oficializacion.html
turbopdf/templates/sistema/hechos_sobrevinientes.html
turbopdf/templates/sistema/hechos_sobrevinientes_vacio.html
turbopdf/templates/sistema/iformfilacuatro.html
turbopdf/templates/sistema/informacion_doble.html
turbopdf/templates/sistema/input_2checks.html
turbopdf/templates/sistema/input_check.html
turbopdf/templates/sistema/input_checkbox.html
turbopdf/templates/sistema/input_solitario.html
turbopdf/templates/sistema/label_input_dos.html
turbopdf/templates/sistema/leyenda_autoriza_correo.html
turbopdf/templates/sistema/leyenda_superiol.html
turbopdf-1.5.5.dist-info/METADATA
turbopdf-1.5.5.dist-info/WHEEL
turbopdf-1.5.5.dist-info/top_level.txt
turbopdf-1.5.5.dist-info/RECORD
