Metadata-Version: 2.4
Name: turbopdf
Version: 1.5.5
Summary: Generador de PDFs simples y rápidos para Python, ideal para entornos educativos y gubernamentales.
Author-email: EcosistemaUNP <ecosistema@unp.gov.co>
License: MIT
Project-URL: Homepage, https://github.com/EcosistemaUNP/python-ecosistema-turbopdf
Project-URL: Repository, https://github.com/EcosistemaUNP/python-ecosistema-turbopdf
Project-URL: Documentation, https://github.com/EcosistemaUNP/python-ecosistema-turbopdf#readme
Project-URL: Changelog, https://github.com/EcosistemaUNP/python-ecosistema-turbopdf/releases
Classifier: Development Status :: 3 - Alpha
Classifier: Intended Audience :: Developers
Classifier: Intended Audience :: Education
Classifier: Intended Audience :: Information Technology
Classifier: License :: OSI Approved :: MIT License
Classifier: Operating System :: OS Independent
Classifier: Programming Language :: Python :: 3
Classifier: Programming Language :: Python :: 3.8
Classifier: Programming Language :: Python :: 3.9
Classifier: Programming Language :: Python :: 3.10
Classifier: Programming Language :: Python :: 3.11
Classifier: Programming Language :: Python :: 3.12
Classifier: Topic :: Software Development :: Libraries :: Python Modules
Requires-Python: >=3.8
Requires-Dist: django>=3.2
Requires-Dist: pdfkit>=1.0.0
